{
 "date": 1669652323948,
 "total": 5,
 "all": [
  {
   "name": "silentsunday",
   "increase": 87.36413300760034,
   "instance": "social.coop",
   "count": "57"
  },
  {
   "name": "standingstonesunday",
   "increase": 66.2621723397902,
   "instance": "social.coop",
   "count": "12"
  },
  {
   "name": "advent",
   "increase": 58.88095239628786,
   "instance": "hostsharing.coop",
   "count": "4"
  },
  {
   "name": "sunday",
   "increase": 32.279999873935395,
   "instance": "social.coop",
   "count": "14"
  },
  {
   "name": "espger",
   "increase": 12.315037627533858,
   "instance": "hostsharing.coop",
   "count": "1"
  }
 ]
}