{
 "date": 1669652323950,
 "total": 5,
 "all": [
  {
   "name": "乌鲁木齐中路",
   "increase": 10.915132019760737,
   "instance": "a.sc",
   "count": "14"
  },
  {
   "name": "china",
   "increase": 6.976230494537225,
   "instance": "a.sc",
   "count": "22"
  },
  {
   "name": "wordpress",
   "increase": 3.2280179330050958,
   "instance": "a.sc",
   "count": "0"
  },
  {
   "name": "shanghai",
   "increase": 3.2044785953846846,
   "instance": "a.sc",
   "count": "5"
  },
  {
   "name": "protests",
   "increase": 2.349984974738227,
   "instance": "a.sc",
   "count": "3"
  }
 ]
}